fico_itr/__init__.py
fico_itr/similarity.py
fico_itr/tasks.py
fico_itr-1.0.0.dist-info/LICENSE
fico_itr-1.0.0.dist-info/METADATA
fico_itr-1.0.0.dist-info/WHEEL
fico_itr-1.0.0.dist-info/top_level.txt
fico_itr-1.0.0.dist-info/RECORD
