Metadata-Version: 2.1
Name: fico-itr
Version: 1.0.0
Summary: Fine-grained and Coarse-grained Image-Text Retrieval Evaluation
Home-page: https://github.com/MikelWL/FiCo-ITR
Author: Mikel Williams Lekuona
Author-email: Mikel Williams Lekuona <m.williams@lboro.ac.uk>
License: MIT License
Project-URL: Homepage, https://github.com/MikelWL/FiCo-ITR
Project-URL: Bug Tracker, https://github.com/MikelWL/FiCo-ITR/issues
Project-URL: Documentation, https://github.com/MikelWL/FiCo-ITR#readme
Keywords: image-text-retrieval,evaluation,benchmark,vision-language
Classifier: Development Status :: 5 - Production/Stable
Classifier: Intended Audience :: Science/Research
Classifier: Topic :: Scientific/Engineering :: Artificial Intelligence
Classifier: License :: OSI Approved :: MIT License
Classifier: Programming Language :: Python :: 3
Classifier: Programming Language :: Python :: 3.7
Classifier: Programming Language :: Python :: 3.8
Classifier: Programming Language :: Python :: 3.9
Classifier: Programming Language :: Python :: 3.10
Classifier: Programming Language :: Python :: 3.11
Classifier: Operating System :: OS Independent
Requires-Python: >=3.7
License-File: LICENSE
Requires-Dist: numpy>=1.19.0
